<?xml version="1.0" encoding="UTF-8" standalone="yes"?><response><header><resultCode>00</resultCode><resultMsg>NORMAL SERVICE.</resultMsg></header><body><item><codeClean>자치관리(직영)</codeClean><codeDisinf>위탁관리</codeDisinf><codeEcon>단일계약</codeEcon><codeElev>위탁관리</codeElev><codeEmgr>상주선임</codeEmgr><codeFalarm>R형</codeFalarm><codeGarbage>차량수거방식</codeGarbage><codeMgr>위탁관리</codeMgr><codeNet>유</codeNet><codeSec>자치관리</codeSec><codeStr>철근콘크리트구조</codeStr><codeWsupply>부스타방식</codeWsupply><educationFacility>초등학교() 중학교() 고등학교(서전고등학교)</educationFacility><kaptCcompany>(주)백운에프엠</kaptCcompany><kaptCode>A10026375</kaptCode><kaptMgrCnt>7</kaptMgrCnt><kaptName>진천건영아모리움양우내안애아파트</kaptName><kaptdCccnt>187</kaptdCccnt><kaptdClcnt>7</kaptdClcnt><kaptdDcnt>3</kaptdDcnt><kaptdEcapa>3000</kaptdEcapa><kaptdEcnt>23</kaptdEcnt><kaptdPcnt>66</kaptdPcnt><kaptdPcntu>1031</kaptdPcntu><kaptdScnt>4</kaptdScnt><kaptdWtimebus>5~10분이내</kaptdWtimebus><welfareFacility>관리사무소, 노인정, 보육시설, 주민공동시설, 어린이놀이터, 휴게시설, 커뮤니티공간, 자전거보관소, 기타</welfareFacility></item></body></response>