<?xml version="1.0" encoding="UTF-8" standalone="yes"?><response><header><resultCode>00</resultCode><resultMsg>NORMAL SERVICE.</resultMsg></header><body><item><codeClean>위탁관리</codeClean><codeDisinf>위탁관리</codeDisinf><codeEcon>종합계약</codeEcon><codeElev>관리방식미정</codeElev><codeEmgr>상주선임</codeEmgr><codeFalarm>R형</codeFalarm><codeGarbage>차량수거방식</codeGarbage><codeMgr>위탁관리</codeMgr><codeNet>유</codeNet><codeSec>위탁관리</codeSec><codeStr>철근콘크리트구조</codeStr><codeWsupply>부스타방식</codeWsupply><convenientFacility>백화점(가든5) 대형상가(스타필드)</convenientFacility><disposalType>독이식</disposalType><kaptCcompany>부강주택관리(주)</kaptCcompany><kaptCode>A10025589</kaptCode><kaptMgrCnt>6</kaptMgrCnt><kaptName>위례포레스트사랑으로부영</kaptName><kaptdCccnt>261</kaptdCccnt><kaptdClcnt>6</kaptdClcnt><kaptdDcnt>4</kaptdDcnt><kaptdEcapa>2800</kaptdEcapa><kaptdEcnt>23</kaptdEcnt><kaptdPcnt>5</kaptdPcnt><kaptdPcntu>926</kaptdPcntu><kaptdScnt>4</kaptdScnt><kaptdSecCom>(주)티에스산업</kaptdSecCom><kaptdWtimebus>5~10분이내</kaptdWtimebus><kaptdWtimesub>20분초과</kaptdWtimesub><subwayLine>8호선</subwayLine><welfareFacility>관리사무소, 노인정, 보육시설, 문고, 주민공동시설, 어린이놀이터, 휴게시설, 커뮤니티공간, 자전거보관소</welfareFacility></item></body></response>