<?xml version="1.0" encoding="UTF-8" standalone="yes"?><response><header><resultCode>00</resultCode><resultMsg>NORMAL SERVICE.</resultMsg></header><body><item><codeClean>자치관리(직영)</codeClean><codeDisinf>위탁관리(총액관리제)</codeDisinf><codeEcon>종합계약</codeEcon><codeElev>위탁관리</codeElev><codeEmgr>위탁선임</codeEmgr><codeFalarm>R형</codeFalarm><codeGarbage>차량수거방식</codeGarbage><codeMgr>위탁관리</codeMgr><codeNet>유</codeNet><codeSec>자치관리(직영)</codeSec><codeWsupply>부스타방식</codeWsupply><convenientFacility>관공서(마포경찰서) 공원(손기정체육)</convenientFacility><disposalType>분무식,기구부착식</disposalType><educationFacility>초등학교(마동, 소의,아현) 중학교(한서) 고등학교(환일, 배문) 대학교(추계예술)</educationFacility><kaptCcompany>세화종합관리</kaptCcompany><kaptCode>A12175202</kaptCode><kaptMgrCnt>8</kaptMgrCnt><kaptName>마포트라팰리스2차</kaptName><kaptdCccnt>60</kaptdCccnt><kaptdClcnt>3</kaptdClcnt><kaptdDcnt>6</kaptdDcnt><kaptdEcapa>1450</kaptdEcapa><kaptdEcnt>6</kaptdEcnt><kaptdPcntu>150</kaptdPcntu><kaptdScnt>2</kaptdScnt><kaptdWtimebus>5~10분이내</kaptdWtimebus><kaptdWtimesub>5분이내</kaptdWtimesub><subwayLine>5호선</subwayLine><subwayStation>애오개역</subwayStation><welfareFacility>관리사무소, 주민공동시설, 어린이놀이터, 자전거보관소, 기타</welfareFacility></item></body></response>