<?xml version="1.0" encoding="UTF-8" standalone="yes"?><response><header><resultCode>00</resultCode><resultMsg>NORMAL SERVICE.</resultMsg></header><body><item><codeClean>위탁관리</codeClean><codeDisinf>위탁관리</codeDisinf><codeEcon>종합계약</codeEcon><codeElev>위탁관리</codeElev><codeEmgr>위탁선임</codeEmgr><codeFalarm>P형</codeFalarm><codeGarbage>음식물쓰레기종량제</codeGarbage><codeMgr>위탁관리</codeMgr><codeNet>무</codeNet><codeSec>위탁관리</codeSec><codeStr>철근콘크리트구조</codeStr><codeWsupply>부스타방식</codeWsupply><convenientFacility>관공서(송파경찰서, 송파소방서) 병원(경찰병원) 백화점(롯데 잠실점) 대형상가(롯데마트, 하나로마트) 공원(올림픽공원)</convenientFacility><disposalType>도포식,분무식</disposalType><educationFacility>초등학교(신가, 가주, 가동, 중대, 평화초) 중학교(석촌, 가락, 송파, 일신여자, 오금, 가원중) 고등학교(가락, 일신여자, 잠실여자, 오금, 방산고) 대학교(한국불교대학교)</educationFacility><kaptCcompany>유원종합관리(주)</kaptCcompany><kaptCode>A13880204</kaptCode><kaptMgrCnt>6</kaptMgrCnt><kaptName>가락대림아파트</kaptName><kaptdCccnt>59</kaptdCccnt><kaptdClcnt>4</kaptdClcnt><kaptdDcnt>30</kaptdDcnt><kaptdEcapa>910</kaptdEcapa><kaptdEcnt>13</kaptdEcnt><kaptdPcnt>270</kaptdPcnt><kaptdPcntu>38</kaptdPcntu><kaptdScnt>8</kaptdScnt><kaptdSecCom>유원종합관리(주)</kaptdSecCom><kaptdWtimebus>5분이내</kaptdWtimebus><subwayLine>8호선</subwayLine><subwayStation>경찰병원</subwayStation><welfareFacility>관리사무소, 노인정, 어린이놀이터</welfareFacility></item></body></response>