<?xml version="1.0" encoding="UTF-8" standalone="yes"?><response><header><resultCode>00</resultCode><resultMsg>NORMAL SERVICE.</resultMsg></header><body><item><codeClean>위탁관리</codeClean><codeDisinf>위탁관리</codeDisinf><codeEcon>단일계약</codeEcon><codeElev>위탁관리</codeElev><codeEmgr>상주선임</codeEmgr><codeFalarm>P형</codeFalarm><codeGarbage>차량수거방식</codeGarbage><codeMgr>위탁관리</codeMgr><codeNet>무</codeNet><codeSec>위탁관리</codeSec><codeStr>철근콘크리트구조</codeStr><codeWsupply>부스타방식</codeWsupply><convenientFacility>관공서(신도림우체국) 병원(제중병원) 대형상가(디큐브시티) 공원(거리공원)</convenientFacility><disposalType>도포식</disposalType><educationFacility>초등학교(미래) 고등학교(구로)</educationFacility><kaptCcompany>(주)경진관리</kaptCcompany><kaptCode>A15283807</kaptCode><kaptMgrCnt>4</kaptMgrCnt><kaptName>LG신도림자이</kaptName><kaptdCccnt>76</kaptdCccnt><kaptdClcnt>2</kaptdClcnt><kaptdDcnt>12</kaptdDcnt><kaptdEcapa>1830</kaptdEcapa><kaptdEcnt>5</kaptdEcnt><kaptdPcnt>42</kaptdPcnt><kaptdPcntu>300</kaptdPcntu><kaptdScnt>3</kaptdScnt><kaptdSecCom>(주)강일기업</kaptdSecCom><kaptdWtimebus>5분이내</kaptdWtimebus><kaptdWtimesub>10~15분이내</kaptdWtimesub><subwayLine>2호선</subwayLine><subwayStation>신도림</subwayStation><welfareFacility>관리사무소, 노인정, 어린이놀이터, 자전거보관소</welfareFacility></item></body></response>