<?xml version="1.0" encoding="UTF-8" standalone="yes"?><response><header><resultCode>00</resultCode><resultMsg>NORMAL SERVICE.</resultMsg></header><body><item><codeClean>위탁관리</codeClean><codeDisinf>위탁관리</codeDisinf><codeEcon>단일계약</codeEcon><codeElev>위탁관리</codeElev><codeEmgr>상주선임</codeEmgr><codeFalarm>R형</codeFalarm><codeGarbage>차량수거방식</codeGarbage><codeMgr>위탁관리</codeMgr><codeNet>유</codeNet><codeSec>위탁관리</codeSec><codeStr>철근콘크리트구조</codeStr><codeWsupply>부스타방식</codeWsupply><convenientFacility>관공서(원곡본동사무소,1동사무소,2동사무소,파출소) 병원(한백의원,차안과의원) 대형상가(보성프라자) 공원(관산,선부제1,시민) 기타(라성호텔,현충탑,중소기업연수원)</convenientFacility><disposalType>도포식,분무식</disposalType><educationFacility>초등학교(원고,서) 중학교(원곡,관산) 고등학교(원곡) 대학교(안산공과)</educationFacility><kaptCcompany>서림주택관리(주)</kaptCcompany><kaptCode>A42513201</kaptCode><kaptMgrCnt>5</kaptMgrCnt><kaptName>한화꿈에그린</kaptName><kaptdCccnt>114</kaptdCccnt><kaptdClcnt>7</kaptdClcnt><kaptdDcnt>4</kaptdDcnt><kaptdEcapa>2200</kaptdEcapa><kaptdEcnt>17</kaptdEcnt><kaptdPcnt>0</kaptdPcnt><kaptdPcntu>782</kaptdPcntu><kaptdScnt>6</kaptdScnt><kaptdSecCom>(유)탄천산업</kaptdSecCom><kaptdWtimebus>10~15분이내</kaptdWtimebus><kaptdWtimesub>10~15분이내</kaptdWtimesub><subwayLine>4호선</subwayLine><subwayStation>안산,공단</subwayStation><welfareFacility>관리사무소, 노인정, 주민공동시설, 어린이놀이터, 자전거보관소</welfareFacility></item></body></response>