<?xml version="1.0" encoding="UTF-8" standalone="yes"?><response><header><resultCode>00</resultCode><resultMsg>NORMAL SERVICE.</resultMsg></header><body><item><codeClean>위탁관리</codeClean><codeDisinf>위탁관리</codeDisinf><codeEcon>단일계약</codeEcon><codeElev>위탁관리</codeElev><codeEmgr>위탁선임</codeEmgr><codeFalarm>R형</codeFalarm><codeGarbage>거점장비수거방식</codeGarbage><codeMgr>위탁관리</codeMgr><codeNet>무</codeNet><codeSec>위탁관리</codeSec><codeStr>철근콘크리트구조</codeStr><codeWsupply>고가수조식</codeWsupply><convenientFacility>관공서(다운동사무소) 병원(강서병원)</convenientFacility><disposalType>분무식,기구부착식</disposalType><educationFacility>초등학교(다운초 다전초) 중학교(다운중학교) 고등학교(다운고등학교)</educationFacility><kaptCcompany>(주)신한종합관리</kaptCcompany><kaptCode>A68180302</kaptCode><kaptMgrCnt>3</kaptMgrCnt><kaptName>다운삼성</kaptName><kaptdCccnt>54</kaptdCccnt><kaptdClcnt>2</kaptdClcnt><kaptdDcnt>5</kaptdDcnt><kaptdEcapa>700</kaptdEcapa><kaptdEcnt>14</kaptdEcnt><kaptdPcnt>123</kaptdPcnt><kaptdPcntu>161</kaptdPcntu><kaptdScnt>2</kaptdScnt><kaptdSecCom>(주)온누리</kaptdSecCom><kaptdWtimebus>5~10분이내</kaptdWtimebus><welfareFacility>관리사무소, 노인정, 어린이놀이터, 자전거보관소</welfareFacility></item></body></response>