<?xml version="1.0" encoding="UTF-8" standalone="yes"?><response><header><resultCode>00</resultCode><resultMsg>NORMAL SERVICE.</resultMsg></header><body><item><bjdCode>4159013500</bjdCode><codeAptNm>아파트</codeAptNm><codeHallNm>복도식</codeHallNm><codeHeatNm>지역난방</codeHeatNm><codeMgrNm>위탁관리</codeMgrNm><codeSaleNm>국민임대</codeSaleNm><doroJuso>경기도 화성시 동탄순환대로10길 42</doroJuso><hoCnt>900</hoCnt><kaptAcompany>한국토지주택공사</kaptAcompany><kaptAddr>경기도 화성시 산척동 747 동탄2LH행복주택35단지</kaptAddr><kaptBcompany>STX 건설</kaptBcompany><kaptCode>A10024841</kaptCode><kaptDongCnt>5</kaptDongCnt><kaptFax>0313763529</kaptFax><kaptMarea>54074.3544</kaptMarea><kaptMparea_135>0</kaptMparea_135><kaptMparea_136>0</kaptMparea_136><kaptMparea_60>900</kaptMparea_60><kaptMparea_85>0</kaptMparea_85><kaptName>동탄2LH행복주택35단지</kaptName><kaptTarea>54512.68</kaptTarea><kaptTel>0313763528</kaptTel><kaptUrl> </kaptUrl><kaptUsedate>20200619</kaptUsedate><kaptdaCnt>900</kaptdaCnt><privArea>26392.26</privArea></item></body></response>