<?xml version="1.0" encoding="UTF-8" standalone="yes"?><response><header><resultCode>00</resultCode><resultMsg>NORMAL SERVICE.</resultMsg></header><body><item><bjdCode>1156010800</bjdCode><codeAptNm>주상복합</codeAptNm><codeHallNm>계단식</codeHallNm><codeHeatNm>개별난방</codeHeatNm><codeMgrNm>위탁관리</codeMgrNm><codeSaleNm>분양</codeSaleNm><doroJuso>서울특별시 영등포구 국회대로50길 20</doroJuso><hoCnt>185</hoCnt><kaptAcompany>영등포1의3재정비촉진구역 도시환경정비사업조합</kaptAcompany><kaptAddr>서울특별시 영등포구 영등포동7가 29-1 포레나영등포센트럴</kaptAddr><kaptBcompany>(주)한화건설</kaptBcompany><kaptCode>A10024567</kaptCode><kaptDongCnt>2</kaptDongCnt><kaptFax>0220691626</kaptFax><kaptMarea>19981.14</kaptMarea><kaptMparea_135>0</kaptMparea_135><kaptMparea_136>0</kaptMparea_136><kaptMparea_60>81</kaptMparea_60><kaptMparea_85>104</kaptMparea_85><kaptName>포레나영등포센트럴</kaptName><kaptTarea>27690.9378</kaptTarea><kaptTel>0220691625</kaptTel><kaptUrl>forenaydp.com</kaptUrl><kaptUsedate>20201026</kaptUsedate><kaptdaCnt>185</kaptdaCnt><privArea>13640.28</privArea></item></body></response>