<?xml version="1.0" encoding="UTF-8" standalone="yes"?><response><header><resultCode>00</resultCode><resultMsg>NORMAL SERVICE.</resultMsg></header><body><item><bjdCode>4684025023</bjdCode><codeHallNm>계단식</codeHallNm><codeHeatNm>개별난방</codeHeatNm><codeMgrNm>위탁관리</codeMgrNm><codeSaleNm>임대</codeSaleNm><doroJuso>전라남도 무안군 하마로 15</doroJuso><hoCnt>208</hoCnt><kaptAcompany>승원팰리체(주)</kaptAcompany><kaptAddr>전라남도 무안군 무안읍 성남리 1002 무안 승원팰리체에코파크</kaptAddr><kaptBcompany>에스원건설</kaptBcompany><kaptCode>A10024236</kaptCode><kaptDongCnt>3</kaptDongCnt><kaptFax>0554528192</kaptFax><kaptMarea>30464.3738</kaptMarea><kaptMparea_135>0</kaptMparea_135><kaptMparea_136>0</kaptMparea_136><kaptMparea_60>0</kaptMparea_60><kaptMparea_85>208</kaptMparea_85><kaptName>무안 승원팰리체에코파크</kaptName><kaptTarea>30856.342</kaptTarea><kaptTel>0614528191</kaptTel><kaptUrl> </kaptUrl><kaptUsedate>20210614</kaptUsedate><kaptdaCnt>208</kaptdaCnt><privArea>17677.6634</privArea></item></body></response>