<?xml version="1.0" encoding="UTF-8" standalone="yes"?><response><header><resultCode>00</resultCode><resultMsg>NORMAL SERVICE.</resultMsg></header><body><item><bjdCode>4121010100</bjdCode><codeAptNm>아파트</codeAptNm><codeHallNm>혼합식</codeHallNm><codeHeatNm>개별난방</codeHeatNm><codeMgrNm>위탁관리</codeMgrNm><codeSaleNm>분양</codeSaleNm><doroJuso>경기도 광명시 새터로 44-8</doroJuso><hoCnt>2104</hoCnt><kaptAcompany>광명제16R구역주택재개발</kaptAcompany><kaptAddr>경기도 광명시 광명동 304-20 광명아크포레자이위브아파트</kaptAddr><kaptBcompany>두산위브/GS자이</kaptBcompany><kaptCode>A10024531</kaptCode><kaptDongCnt>19</kaptDongCnt><kaptFax>0220602716</kaptFax><kaptMarea>166690.0579</kaptMarea><kaptMparea_135>0</kaptMparea_135><kaptMparea_136>0</kaptMparea_136><kaptMparea_60>1490</kaptMparea_60><kaptMparea_85>614</kaptMparea_85><kaptName>광명아크포레자이위브아파트</kaptName><kaptTarea>258575.56</kaptTarea><kaptTel>0220602715</kaptTel><kaptUrl>gmeco.xisnd.co.kr</kaptUrl><kaptUsedate>20201126</kaptUsedate><kaptdaCnt>2104</kaptdaCnt><privArea>126104.6455</privArea></item></body></response>