<?xml version="1.0" encoding="UTF-8" standalone="yes"?><response><header><resultCode>00</resultCode><resultMsg>NORMAL SERVICE.</resultMsg></header><body><item><bjdCode>4145011000</bjdCode><codeAptNm>아파트</codeAptNm><codeHallNm>계단식</codeHallNm><codeHeatNm>지역난방</codeHeatNm><codeMgrNm>위탁관리</codeMgrNm><codeSaleNm>분양</codeSaleNm><doroJuso>경기도 하남시 세미로1길 10</doroJuso><hoCnt>404</hoCnt><kaptAcompany>하남마블링시티개발(주)</kaptAcompany><kaptAddr>경기도 하남시 풍산동 630 하남힐즈파크푸르지오1단지</kaptAddr><kaptBcompany>대우건설(주)</kaptBcompany><kaptCode>A10024890</kaptCode><kaptDongCnt>7</kaptDongCnt><kaptFax>0317963307</kaptFax><kaptMarea>32033.7972</kaptMarea><kaptMparea_135>0</kaptMparea_135><kaptMparea_136>0</kaptMparea_136><kaptMparea_60>404</kaptMparea_60><kaptMparea_85>0</kaptMparea_85><kaptName>하남힐즈파크푸르지오1단지</kaptName><kaptTarea>53683</kaptTarea><kaptTel>0317963306</kaptTel><kaptUrl> </kaptUrl><kaptUsedate>20200427</kaptUsedate><kaptdaCnt>404</kaptdaCnt><privArea>23333.3629</privArea></item></body></response>