<?xml version="1.0" encoding="UTF-8" standalone="yes"?><response><header><resultCode>00</resultCode><resultMsg>NORMAL SERVICE.</resultMsg></header><body><item><bjdCode>4157010900</bjdCode><codeAptNm>아파트</codeAptNm><codeHallNm>계단식</codeHallNm><codeHeatNm>지역난방</codeHeatNm><codeMgrNm>위탁관리</codeMgrNm><codeSaleNm>분양</codeSaleNm><doroJuso>경기도 김포시 김포한강4로 471</doroJuso><hoCnt>344</hoCnt><kaptAcompany>(주)스카이리빙</kaptAcompany><kaptAddr>경기도 김포시 구래동 6887-1 호반베르디움 더 레이크 2차</kaptAddr><kaptBcompany>호반건설</kaptBcompany><kaptCode>A10025936</kaptCode><kaptDongCnt>5</kaptDongCnt><kaptFax>0319964402</kaptFax><kaptMarea>38189.765</kaptMarea><kaptMparea_135>0</kaptMparea_135><kaptMparea_136>0</kaptMparea_136><kaptMparea_60>0</kaptMparea_60><kaptMparea_85>344</kaptMparea_85><kaptName>호반베르디움 더 레이크 2차</kaptName><kaptTarea>56206.0245</kaptTarea><kaptTel>0319964401</kaptTel><kaptUrl> </kaptUrl><kaptUsedate>20181102</kaptUsedate><kaptdaCnt>344</kaptdaCnt><privArea>28554.1009</privArea></item></body></response>