<?xml version="1.0" encoding="UTF-8" standalone="yes"?><response><header><resultCode>00</resultCode><resultMsg>NORMAL SERVICE.</resultMsg></header><body><item><bjdCode>4413310800</bjdCode><codeAptNm>아파트</codeAptNm><codeHallNm>계단식</codeHallNm><codeHeatNm>지역난방</codeHeatNm><codeMgrNm>위탁관리</codeMgrNm><codeSaleNm>분양</codeSaleNm><doroJuso>충청남도 천안시 서북구 불당26로 50</doroJuso><hoCnt>355</hoCnt><kaptAcompany>(주)신영</kaptAcompany><kaptAddr>충청남도 천안서북구 불당동 1614 천안불당지웰시티푸르지오 2단지아파트</kaptAddr><kaptBcompany>대우건설</kaptBcompany><kaptCode>A10026465</kaptCode><kaptDongCnt>4</kaptDongCnt><kaptFax>0416227538</kaptFax><kaptMarea>64526.0889</kaptMarea><kaptMparea_135>355</kaptMparea_135><kaptMparea_136>0</kaptMparea_136><kaptMparea_60>0</kaptMparea_60><kaptMparea_85>0</kaptMparea_85><kaptName>천안불당지웰시티푸르지오 2단지아파트</kaptName><kaptTarea>137747.0418</kaptTarea><kaptTel>0416227537</kaptTel><kaptUrl>천안불당지웰시티푸르지오2단지.apti.co.kr</kaptUrl><kaptUsedate>20171227</kaptUsedate><kaptdaCnt>355</kaptdaCnt><privArea>36547.2731</privArea></item></body></response>