<?xml version="1.0" encoding="UTF-8" standalone="yes"?><response><header><resultCode>00</resultCode><resultMsg>NORMAL SERVICE.</resultMsg></header><body><item><bjdCode>2635010400</bjdCode><codeAptNm>아파트</codeAptNm><codeHallNm>혼합식</codeHallNm><codeHeatNm>개별난방</codeHeatNm><codeMgrNm>위탁관리</codeMgrNm><codeSaleNm>분양</codeSaleNm><doroJuso>부산광역시 해운대구 해운대로76번길 40</doroJuso><hoCnt>753</hoCnt><kaptAcompany>재송2구역 주택재개발정비사업 조합</kaptAcompany><kaptAddr>부산광역시 해운대구 재송동 938 센텀리슈빌 아파트</kaptAddr><kaptBcompany>계룡건설</kaptBcompany><kaptCode>A10026557</kaptCode><kaptDongCnt>8</kaptDongCnt><kaptFax>0517843831</kaptFax><kaptMarea>82332.78</kaptMarea><kaptMparea_135>64</kaptMparea_135><kaptMparea_136>0</kaptMparea_136><kaptMparea_60>126</kaptMparea_60><kaptMparea_85>563</kaptMparea_85><kaptName>센텀리슈빌 아파트</kaptName><kaptTarea>110528.8597</kaptTarea><kaptTel>0517843830</kaptTel><kaptUrl> </kaptUrl><kaptUsedate>20171222</kaptUsedate><kaptdaCnt>753</kaptdaCnt><privArea>61137.3456</privArea></item></body></response>