<?xml version="1.0" encoding="UTF-8" standalone="yes"?><response><header><resultCode>00</resultCode><resultMsg>NORMAL SERVICE.</resultMsg></header><body><item><bjdCode>4375025325</bjdCode><codeAptNm>아파트</codeAptNm><codeHallNm>계단식</codeHallNm><codeHeatNm>개별난방</codeHeatNm><codeMgrNm>위탁관리</codeMgrNm><codeSaleNm>임대</codeSaleNm><doroJuso>충청북도 진천군 연미로 87</doroJuso><hoCnt>924</hoCnt><kaptAcompany>LH</kaptAcompany><kaptAddr>충청북도 진천군 덕산읍 두촌리 2494 천년나무4단지아파트</kaptAddr><kaptBcompany>동문건설(주)</kaptBcompany><kaptCode>A10027003</kaptCode><kaptDongCnt>8</kaptDongCnt><kaptFax>0435360014</kaptFax><kaptMarea>106626.813</kaptMarea><kaptMparea_135>0</kaptMparea_135><kaptMparea_136>0</kaptMparea_136><kaptMparea_60>924</kaptMparea_60><kaptMparea_85>0</kaptMparea_85><kaptName>천년나무4단지아파트</kaptName><kaptTarea>107069.464</kaptTarea><kaptTel>0435360013</kaptTel><kaptUrl>cafe.naver.com/1000a4</kaptUrl><kaptUsedate>20170524</kaptUsedate><kaptdaCnt>924</kaptdaCnt><privArea>55419.78</privArea></item></body></response>