<?xml version="1.0" encoding="UTF-8" standalone="yes"?><response><header><resultCode>00</resultCode><resultMsg>NORMAL SERVICE.</resultMsg></header><body><item><bjdCode>1168011200</bjdCode><codeAptNm>아파트</codeAptNm><codeHallNm>계단식</codeHallNm><codeHeatNm>지역난방</codeHeatNm><codeMgrNm>위탁관리</codeMgrNm><codeSaleNm>임대+분양</codeSaleNm><doroJuso>서울특별시 강남구 자곡로 175</doroJuso><hoCnt>716</hoCnt><kaptAcompany>계룡건설산업(주)</kaptAcompany><kaptAddr>서울특별시 강남구 자곡동 602 LH강남아이파크아파트</kaptAddr><kaptBcompany>한국토지주택공사</kaptBcompany><kaptCode>A10028172</kaptCode><kaptDongCnt>10</kaptDongCnt><kaptFax>024591132</kaptFax><kaptMarea>102814.1439</kaptMarea><kaptMparea_135>0</kaptMparea_135><kaptMparea_136>0</kaptMparea_136><kaptMparea_60>195</kaptMparea_60><kaptMparea_85>521</kaptMparea_85><kaptName>LH강남아이파크아파트</kaptName><kaptTarea>102988.17</kaptTarea><kaptTel>024591131</kaptTel><kaptUrl> </kaptUrl><kaptUsedate>20141002</kaptUsedate><kaptdaCnt>716</kaptdaCnt><privArea>52663.06</privArea></item></body></response>