<?xml version="1.0" encoding="UTF-8" standalone="yes"?><response><header><resultCode>00</resultCode><resultMsg>NORMAL SERVICE.</resultMsg></header><body><item><bjdCode>5013011200</bjdCode><codeAptNm>아파트</codeAptNm><codeHallNm>계단식</codeHallNm><codeHeatNm>개별난방</codeHeatNm><codeMgrNm>위탁관리</codeMgrNm><codeSaleNm>분양</codeSaleNm><doroJuso>제주특별자치도 서귀포시 중문상로82번길 15</doroJuso><hoCnt>290</hoCnt><kaptAcompany>남해주택(주)</kaptAcompany><kaptAddr>제주특별자치도 서귀포시 중문동 1725 중문남해오네뜨오션힐</kaptAddr><kaptBcompany>남해종합건설(주)</kaptBcompany><kaptCode>A10026817</kaptCode><kaptDongCnt>15</kaptDongCnt><kaptFax>0647398834</kaptFax><kaptMarea>30085.21</kaptMarea><kaptMparea_135>0</kaptMparea_135><kaptMparea_136>0</kaptMparea_136><kaptMparea_60>0</kaptMparea_60><kaptMparea_85>290</kaptMparea_85><kaptName>중문남해오네뜨오션힐</kaptName><kaptTarea>36663.31</kaptTarea><kaptTel>0647397734</kaptTel><kaptUrl> </kaptUrl><kaptUsedate>20161206</kaptUsedate><kaptdaCnt>290</kaptdaCnt><privArea>23341.3</privArea></item></body></response>