<?xml version="1.0" encoding="UTF-8" standalone="yes"?><response><header><resultCode>00</resultCode><resultMsg>NORMAL SERVICE.</resultMsg></header><body><item><bjdCode>2826012100</bjdCode><codeAptNm>아파트</codeAptNm><codeHallNm>계단식</codeHallNm><codeHeatNm>개별난방</codeHeatNm><codeMgrNm>위탁관리</codeMgrNm><codeSaleNm>분양</codeSaleNm><doroJuso>인천광역시 서구 검단로 841</doroJuso><hoCnt>138</hoCnt><kaptAcompany>한일건설(주)</kaptAcompany><kaptAddr>인천광역시 서구 불로동 178 불로한일타운아파트</kaptAddr><kaptBcompany>한일건설(주)</kaptBcompany><kaptCode>A10025430</kaptCode><kaptDongCnt>2</kaptDongCnt><kaptFax>0325691502</kaptFax><kaptMarea>13509.87</kaptMarea><kaptMparea_135>0</kaptMparea_135><kaptMparea_136>0</kaptMparea_136><kaptMparea_60>67</kaptMparea_60><kaptMparea_85>71</kaptMparea_85><kaptName>불로한일타운아파트</kaptName><kaptTarea>16608</kaptTarea><kaptTel>0325691501</kaptTel><kaptUrl> </kaptUrl><kaptUsedate>20080425</kaptUsedate><kaptdaCnt>138</kaptdaCnt><privArea>9996.48</privArea></item></body></response>