<?xml version="1.0" encoding="UTF-8" standalone="yes"?><response><header><resultCode>00</resultCode><resultMsg>NORMAL SERVICE.</resultMsg></header><body><item><bjdCode>3120010600</bjdCode><codeAptNm>아파트</codeAptNm><codeHallNm>계단식</codeHallNm><codeHeatNm>개별난방</codeHeatNm><codeMgrNm>위탁관리</codeMgrNm><codeSaleNm>분양</codeSaleNm><doroJuso>울산광역시 북구 중산로 47</doroJuso><hoCnt>739</hoCnt><kaptAcompany>미라주건설(주)</kaptAcompany><kaptAddr>울산광역시 북구 중산동 19-13 U-스타시티일동미라주더스타2단지</kaptAddr><kaptBcompany>(주)일동</kaptBcompany><kaptCode>A10025842</kaptCode><kaptDongCnt>12</kaptDongCnt><kaptFax>0522986639</kaptFax><kaptMarea>77853.8987</kaptMarea><kaptMparea_135>41</kaptMparea_135><kaptMparea_136>0</kaptMparea_136><kaptMparea_60>119</kaptMparea_60><kaptMparea_85>579</kaptMparea_85><kaptName>U-스타시티일동미라주더스타2단지</kaptName><kaptTarea>109217.6364</kaptTarea><kaptTel>0522976639</kaptTel><kaptUrl> </kaptUrl><kaptUsedate>20181221</kaptUsedate><kaptdaCnt>739</kaptdaCnt><privArea>58317.011</privArea></item></body></response>