<?xml version="1.0" encoding="UTF-8" standalone="yes"?><response><header><resultCode>00</resultCode><resultMsg>NORMAL SERVICE.</resultMsg></header><body><item><bjdCode>1141011100</bjdCode><codeAptNm>아파트</codeAptNm><codeHallNm>계단식</codeHallNm><codeHeatNm>개별난방</codeHeatNm><codeMgrNm>위탁관리</codeMgrNm><codeSaleNm>분양</codeSaleNm><doroJuso>서울특별시 서대문구 통일로39가길 57</doroJuso><hoCnt>704</hoCnt><kaptAcompany>홍제11구역 재개발조합</kaptAcompany><kaptAddr>서울특별시 서대문구 홍제동 331 홍제현대아파트</kaptAddr><kaptBcompany>현대산업개발</kaptBcompany><kaptCode>A12009102</kaptCode><kaptDongCnt>8</kaptDongCnt><kaptFax>023962958</kaptFax><kaptMarea>80524.7</kaptMarea><kaptMparea_135>264</kaptMparea_135><kaptMparea_136>0</kaptMparea_136><kaptMparea_60>0</kaptMparea_60><kaptMparea_85>440</kaptMparea_85><kaptName>홍제현대아파트</kaptName><kaptTarea>86368.43</kaptTarea><kaptTel>023950791</kaptTel><kaptUrl> </kaptUrl><kaptUsedate>19920708</kaptUsedate><kaptdaCnt>704</kaptdaCnt><privArea>63142.32</privArea></item></body></response>