<?xml version="1.0" encoding="UTF-8" standalone="yes"?><response><header><resultCode>00</resultCode><resultMsg>NORMAL SERVICE.</resultMsg></header><body><item><bjdCode>1168011800</bjdCode><codeAptNm>주상복합</codeAptNm><codeHallNm>계단식</codeHallNm><codeHeatNm>지역난방</codeHeatNm><codeMgrNm>위탁관리</codeMgrNm><codeSaleNm>분양</codeSaleNm><hoCnt>414</hoCnt><kaptAcompany>라성건설(주)</kaptAcompany><kaptAddr>서울특별시 강남구 도곡동 467-7 아카데미스위트</kaptAddr><kaptBcompany>라성건설(주)</kaptBcompany><kaptCode>A13527011</kaptCode><kaptDongCnt>1</kaptDongCnt><kaptFax>025744305</kaptFax><kaptMarea>52956.02</kaptMarea><kaptMparea_135>220</kaptMparea_135><kaptMparea_136>106</kaptMparea_136><kaptMparea_60>0</kaptMparea_60><kaptMparea_85>88</kaptMparea_85><kaptName>아카데미스위트</kaptName><kaptTarea>102379.47</kaptTarea><kaptTel>025734305</kaptTel><kaptUrl>academysweet.com/</kaptUrl><kaptUsedate>20041115</kaptUsedate><kaptdaCnt>414</kaptdaCnt><privArea>52865.18</privArea></item></body></response>