<?xml version="1.0" encoding="UTF-8" standalone="yes"?><response><header><resultCode>00</resultCode><resultMsg>NORMAL SERVICE.</resultMsg></header><body><item><bjdCode>1135010600</bjdCode><codeAptNm>아파트</codeAptNm><codeHallNm>혼합식</codeHallNm><codeHeatNm>개별난방</codeHeatNm><codeMgrNm>위탁관리</codeMgrNm><codeSaleNm>분양</codeSaleNm><doroJuso>서울특별시 노원구 중계로14나길 25</doroJuso><hoCnt>478</hoCnt><kaptAcompany>삼성중공업</kaptAcompany><kaptAddr>서울특별시 노원구 중계동 593 중계삼성</kaptAddr><kaptBcompany>삼성중공업</kaptBcompany><kaptCode>A13922908</kaptCode><kaptDongCnt>7</kaptDongCnt><kaptFax>029340137</kaptFax><kaptMarea>50757.0208</kaptMarea><kaptMparea_135>117</kaptMparea_135><kaptMparea_136>0</kaptMparea_136><kaptMparea_60>201</kaptMparea_60><kaptMparea_85>160</kaptMparea_85><kaptName>중계삼성</kaptName><kaptTarea>68644.62</kaptTarea><kaptTel>029340131</kaptTel><kaptUrl> </kaptUrl><kaptUsedate>19991030</kaptUsedate><kaptdaCnt>478</kaptdaCnt><privArea>38998.47</privArea></item></body></response>