<?xml version="1.0" encoding="UTF-8" standalone="yes"?><response><header><resultCode>00</resultCode><resultMsg>NORMAL SERVICE.</resultMsg></header><body><item><bjdCode>1121510500</bjdCode><codeAptNm>아파트</codeAptNm><codeHallNm>계단식</codeHallNm><codeHeatNm>개별난방</codeHeatNm><codeMgrNm>위탁관리</codeMgrNm><codeSaleNm>분양</codeSaleNm><doroJuso>서울특별시 광진구 뚝섬로36길 19</doroJuso><hoCnt>257</hoCnt><kaptAcompany>자양2지구 재건축 주택조합</kaptAcompany><kaptAddr>서울특별시 광진구 자양동 789 자양현대홈타운8차</kaptAddr><kaptBcompany>현대건설(주)</kaptBcompany><kaptCode>A14319007</kaptCode><kaptDongCnt>5</kaptDongCnt><kaptFax>0234379298</kaptFax><kaptMarea>28391.5</kaptMarea><kaptMparea_135>76</kaptMparea_135><kaptMparea_136>0</kaptMparea_136><kaptMparea_60>0</kaptMparea_60><kaptMparea_85>181</kaptMparea_85><kaptName>자양현대홈타운8차</kaptName><kaptTarea>36671.5</kaptTarea><kaptTel>0234379297</kaptTel><kaptUrl>홈페이지 없음</kaptUrl><kaptUsedate>20020508</kaptUsedate><kaptdaCnt>257</kaptdaCnt><privArea>22805.75</privArea></item></body></response>