<?xml version="1.0" encoding="UTF-8" standalone="yes"?><response><header><resultCode>00</resultCode><resultMsg>NORMAL SERVICE.</resultMsg></header><body><item><bjdCode>4211012300</bjdCode><codeAptNm>아파트</codeAptNm><codeHallNm>계단식</codeHallNm><codeHeatNm>중앙난방</codeHeatNm><codeMgrNm>위탁관리</codeMgrNm><codeSaleNm>분양</codeSaleNm><doroJuso>강원도 춘천시 춘주로 174</doroJuso><hoCnt>620</hoCnt><kaptAcompany>삼익건설. 코오롱건설</kaptAcompany><kaptAddr>강원도 춘천시 퇴계동 916-3 그린타운아파트</kaptAddr><kaptBcompany>삼익건설. 코오롱건설</kaptBcompany><kaptCode>A20094617</kaptCode><kaptDongCnt>8</kaptDongCnt><kaptFax>0332430582</kaptFax><kaptMarea>84054.14</kaptMarea><kaptMparea_135>620</kaptMparea_135><kaptMparea_136>0</kaptMparea_136><kaptMparea_60>0</kaptMparea_60><kaptMparea_85>0</kaptMparea_85><kaptName>그린타운아파트</kaptName><kaptTarea>84054.14</kaptTarea><kaptTel>0332579752</kaptTel><kaptUrl> </kaptUrl><kaptUsedate>19941121</kaptUsedate><kaptdaCnt>620</kaptdaCnt><privArea>69748.2</privArea></item></body></response>