<?xml version="1.0" encoding="UTF-8" standalone="yes"?><response><header><resultCode>00</resultCode><resultMsg>NORMAL SERVICE.</resultMsg></header><body><item><bjdCode>4413111400</bjdCode><codeAptNm>아파트</codeAptNm><codeHallNm>계단식</codeHallNm><codeHeatNm>개별난방</codeHeatNm><codeMgrNm>위탁관리</codeMgrNm><codeSaleNm>분양</codeSaleNm><doroJuso>충청남도 천안시 동남구 다가말2길 54</doroJuso><hoCnt>245</hoCnt><kaptAcompany>대한토지신탁</kaptAcompany><kaptAddr>충청남도 천안동남구 다가동 444-3 다가한화 꿈에그린 아파트</kaptAddr><kaptBcompany>한화건설</kaptBcompany><kaptCode>A33011003</kaptCode><kaptDongCnt>5</kaptDongCnt><kaptFax>0415752023</kaptFax><kaptMarea>27204.8</kaptMarea><kaptMparea_135>0</kaptMparea_135><kaptMparea_136>0</kaptMparea_136><kaptMparea_60>0</kaptMparea_60><kaptMparea_85>245</kaptMparea_85><kaptName>다가한화 꿈에그린 아파트</kaptName><kaptTarea>31712.35</kaptTarea><kaptTel>0415752022</kaptTel><kaptUrl>다가한화.apti.co.kr</kaptUrl><kaptUsedate>20060228</kaptUsedate><kaptdaCnt>245</kaptdaCnt><privArea>20815.2</privArea></item></body></response>