<?xml version="1.0" encoding="UTF-8" standalone="yes"?><response><header><resultCode>00</resultCode><resultMsg>NORMAL SERVICE.</resultMsg></header><body><item><bjdCode>4372025024</bjdCode><codeAptNm>아파트</codeAptNm><codeHallNm>복도식</codeHallNm><codeHeatNm>개별난방</codeHeatNm><codeMgrNm>자치관리</codeMgrNm><codeSaleNm>분양</codeSaleNm><doroJuso>충청북도 보은군 향교1길 11-3</doroJuso><hoCnt>220</hoCnt><kaptAcompany>극동</kaptAcompany><kaptAddr>충청북도 보은군 보은읍 교사리 402-29 보은극동아파트</kaptAddr><kaptBcompany>극동</kaptBcompany><kaptCode>A37680301</kaptCode><kaptDongCnt>3</kaptDongCnt><kaptFax>0435438283</kaptFax><kaptMarea>12958.682</kaptMarea><kaptMparea_135>0</kaptMparea_135><kaptMparea_136>0</kaptMparea_136><kaptMparea_60>220</kaptMparea_60><kaptMparea_85>0</kaptMparea_85><kaptName>보은극동아파트</kaptName><kaptTarea>13190</kaptTarea><kaptTel>0435438286</kaptTel><kaptUrl>sunchan5393 hanmail.net</kaptUrl><kaptUsedate>19971030</kaptUsedate><kaptdaCnt>220</kaptdaCnt><privArea>9520.8</privArea></item></body></response>