<?xml version="1.0" encoding="UTF-8" standalone="yes"?><response><header><resultCode>00</resultCode><resultMsg>NORMAL SERVICE.</resultMsg></header><body><item><bjdCode>4128110600</bjdCode><codeAptNm>아파트</codeAptNm><codeHallNm>계단식</codeHallNm><codeHeatNm>지역난방</codeHeatNm><codeMgrNm>위탁관리</codeMgrNm><codeSaleNm>분양</codeSaleNm><doroJuso>경기도 고양시 덕양구 호국로742번길 53</doroJuso><hoCnt>480</hoCnt><kaptAcompany>(주)삼보종합건설</kaptAcompany><kaptAddr>경기도 고양덕양구 성사동 726 신원당8단지삼보아파트</kaptAddr><kaptBcompany>(주)삼보종합건설</kaptBcompany><kaptCode>A41280803</kaptCode><kaptDongCnt>4</kaptDongCnt><kaptFax>0319657227</kaptFax><kaptMarea>61825.6</kaptMarea><kaptMparea_135>320</kaptMparea_135><kaptMparea_136>0</kaptMparea_136><kaptMparea_60>0</kaptMparea_60><kaptMparea_85>160</kaptMparea_85><kaptName>신원당8단지삼보아파트</kaptName><kaptTarea>64370.21</kaptTarea><kaptTel>0319643684</kaptTel><kaptUrl>성사신원당8단지삼보.ma-um.co.kr</kaptUrl><kaptUsedate>19921009</kaptUsedate><kaptdaCnt>480</kaptdaCnt><privArea>50121.6</privArea></item></body></response>