<?xml version="1.0" encoding="UTF-8" standalone="yes"?><response><header><resultCode>00</resultCode><resultMsg>NORMAL SERVICE.</resultMsg></header><body><item><bjdCode>4128112300</bjdCode><codeAptNm>아파트</codeAptNm><codeHallNm>계단식</codeHallNm><codeHeatNm>지역난방</codeHeatNm><codeMgrNm>위탁관리</codeMgrNm><codeSaleNm>분양</codeSaleNm><doroJuso>경기도 고양시 덕양구 화중로 164</doroJuso><hoCnt>2032</hoCnt><kaptAcompany>삼익주택,삼익건설,삼성건설,LG건설,(주)신성,(주)미도파</kaptAcompany><kaptAddr>경기도 고양덕양구 화정동 870 화정은빛마을5단지</kaptAddr><kaptBcompany>삼성,LG,삼익건설,삼익주택,미도파,신성</kaptBcompany><kaptCode>A41282606</kaptCode><kaptDongCnt>38</kaptDongCnt><kaptFax>0319648697</kaptFax><kaptMarea>322493.44</kaptMarea><kaptMparea_135>1616</kaptMparea_135><kaptMparea_136>416</kaptMparea_136><kaptMparea_60>0</kaptMparea_60><kaptMparea_85>0</kaptMparea_85><kaptName>화정은빛마을5단지</kaptName><kaptTarea>382241.506</kaptTarea><kaptTel>0319696141</kaptTel><kaptUrl>은빛마을5단지.ma-um.co.kr</kaptUrl><kaptUsedate>19951113</kaptUsedate><kaptdaCnt>2032</kaptdaCnt><privArea>265505.6</privArea></item></body></response>