<?xml version="1.0" encoding="UTF-8" standalone="yes"?><response><header><resultCode>00</resultCode><resultMsg>NORMAL SERVICE.</resultMsg></header><body><item><bjdCode>4121010400</bjdCode><codeAptNm>아파트</codeAptNm><codeHallNm>혼합식</codeHallNm><codeHeatNm>개별난방</codeHeatNm><codeMgrNm>위탁관리</codeMgrNm><codeSaleNm>분양</codeSaleNm><doroJuso>경기도 광명시 하안로 172</doroJuso><hoCnt>247</hoCnt><kaptAcompany>소하1동 재건축 주택조합</kaptAcompany><kaptAddr>경기도 광명시 소하동 48-13 소하삼익</kaptAddr><kaptBcompany>삼익건설(주)</kaptBcompany><kaptCode>A42382103</kaptCode><kaptDongCnt>2</kaptDongCnt><kaptFax>028979563</kaptFax><kaptMarea>24061.03</kaptMarea><kaptMparea_135>0</kaptMparea_135><kaptMparea_136>0</kaptMparea_136><kaptMparea_60>151</kaptMparea_60><kaptMparea_85>96</kaptMparea_85><kaptName>소하삼익</kaptName><kaptTarea>30751.939</kaptTarea><kaptTel>028976934</kaptTel><kaptUrl>광명삼익아파트.ma-um.co.kr</kaptUrl><kaptUsedate>19980701</kaptUsedate><kaptdaCnt>247</kaptdaCnt><privArea>17206.755</privArea></item></body></response>