<?xml version="1.0" encoding="UTF-8" standalone="yes"?><response><header><resultCode>00</resultCode><resultMsg>NORMAL SERVICE.</resultMsg></header><body><item><bjdCode>4117310100</bjdCode><codeAptNm>주상복합</codeAptNm><codeHallNm>계단식</codeHallNm><codeHeatNm>개별난방</codeHeatNm><codeMgrNm>위탁관리</codeMgrNm><codeSaleNm>분양</codeSaleNm><doroJuso>경기도 안양시 동안구 경수대로 947</doroJuso><hoCnt>191</hoCnt><kaptAcompany>화성개발(주)</kaptAcompany><kaptAddr>경기도 안양동안구 비산동 1166 비산화성파크드림</kaptAddr><kaptBcompany>화성개발(주)</kaptBcompany><kaptCode>A43105006</kaptCode><kaptDongCnt>2</kaptDongCnt><kaptFax>0314660958</kaptFax><kaptMarea>29829.7879</kaptMarea><kaptMparea_135>20</kaptMparea_135><kaptMparea_136>0</kaptMparea_136><kaptMparea_60>0</kaptMparea_60><kaptMparea_85>171</kaptMparea_85><kaptName>비산화성파크드림</kaptName><kaptTarea>33189.61</kaptTarea><kaptTel>0314660957</kaptTel><kaptUrl>bisanparkdream.com</kaptUrl><kaptUsedate>20141024</kaptUsedate><kaptdaCnt>191</kaptdaCnt><privArea>16202.2218</privArea></item></body></response>