<?xml version="1.0" encoding="UTF-8" standalone="yes"?><response><header><resultCode>00</resultCode><resultMsg>NORMAL SERVICE.</resultMsg></header><body><item><bjdCode>4159011900</bjdCode><codeAptNm>아파트</codeAptNm><codeHallNm>계단식</codeHallNm><codeHeatNm>개별난방</codeHeatNm><codeMgrNm>위탁관리</codeMgrNm><codeSaleNm>분양</codeSaleNm><doroJuso>경기도 화성시 동탄지성로 333</doroJuso><hoCnt>621</hoCnt><kaptAcompany>삼성물산</kaptAcompany><kaptAddr>경기도 화성시 기산동 464 행림마을삼성래미안1차</kaptAddr><kaptBcompany>엘디산업</kaptBcompany><kaptCode>A44577601</kaptCode><kaptDongCnt>10</kaptDongCnt><kaptFax>0312363726</kaptFax><kaptMarea>68688.027</kaptMarea><kaptMparea_135>60</kaptMparea_135><kaptMparea_136>0</kaptMparea_136><kaptMparea_60>0</kaptMparea_60><kaptMparea_85>561</kaptMparea_85><kaptName>행림마을삼성래미안1차</kaptName><kaptTarea>82388.406</kaptTarea><kaptTel>0312363721</kaptTel><kaptUrl>www.apt464.com</kaptUrl><kaptUsedate>20031231</kaptUsedate><kaptdaCnt>621</kaptdaCnt><privArea>54472.407</privArea></item></body></response>