<?xml version="1.0" encoding="UTF-8" standalone="yes"?><response><header><resultCode>00</resultCode><resultMsg>NORMAL SERVICE.</resultMsg></header><body><item><bjdCode>2917012700</bjdCode><codeAptNm>아파트</codeAptNm><codeHallNm>복도식</codeHallNm><codeHeatNm>개별난방</codeHeatNm><codeMgrNm>자치관리</codeMgrNm><codeSaleNm>분양</codeSaleNm><doroJuso>광주광역시 북구 설죽로 535-1</doroJuso><hoCnt>650</hoCnt><kaptAcompany>(주)한국토지신탁</kaptAcompany><kaptAddr>광주광역시 북구 일곡동 849-2 일곡청솔1차아파트</kaptAddr><kaptBcompany>(주)광토건설</kaptBcompany><kaptCode>A50086714</kaptCode><kaptDongCnt>4</kaptDongCnt><kaptFax>0624622011</kaptFax><kaptMarea>43329</kaptMarea><kaptMparea_135>0</kaptMparea_135><kaptMparea_136>0</kaptMparea_136><kaptMparea_60>650</kaptMparea_60><kaptMparea_85>0</kaptMparea_85><kaptName>일곡청솔1차아파트</kaptName><kaptTarea>51250.47</kaptTarea><kaptTel>0625752011</kaptTel><kaptUrl>gb226.gamis.or.kr</kaptUrl><kaptUsedate>20001026</kaptUsedate><kaptdaCnt>650</kaptdaCnt><privArea>31492.5</privArea></item></body></response>