<?xml version="1.0" encoding="UTF-8" standalone="yes"?><response><header><resultCode>00</resultCode><resultMsg>NORMAL SERVICE.</resultMsg></header><body><item><bjdCode>2914012000</bjdCode><codeAptNm>아파트</codeAptNm><codeHallNm>계단식</codeHallNm><codeHeatNm>개별난방</codeHeatNm><codeMgrNm>자치관리</codeMgrNm><codeSaleNm>분양</codeSaleNm><doroJuso>광주광역시 서구 상무시민로 65</doroJuso><hoCnt>270</hoCnt><kaptAcompany>한국건설</kaptAcompany><kaptAddr>광주광역시 서구 치평동 1166-5 한국아파트</kaptAddr><kaptBcompany>한국건설</kaptBcompany><kaptCode>A50282902</kaptCode><kaptDongCnt>4</kaptDongCnt><kaptFax>0623723194</kaptFax><kaptMarea>21421.476</kaptMarea><kaptMparea_135>0</kaptMparea_135><kaptMparea_136>0</kaptMparea_136><kaptMparea_60>270</kaptMparea_60><kaptMparea_85>0</kaptMparea_85><kaptName>한국아파트</kaptName><kaptTarea>24247.37</kaptTarea><kaptTel>0624563194</kaptTel><kaptUrl>gamis.or.kr</kaptUrl><kaptUsedate>19980330</kaptUsedate><kaptdaCnt>270</kaptdaCnt><privArea>16189.05</privArea></item></body></response>