<?xml version="1.0" encoding="UTF-8" standalone="yes"?><response><header><resultCode>00</resultCode><resultMsg>NORMAL SERVICE.</resultMsg></header><body><item><bjdCode>4687025036</bjdCode><codeAptNm>아파트</codeAptNm><codeHallNm>계단식</codeHallNm><codeHeatNm>개별난방</codeHeatNm><codeMgrNm>자치관리</codeMgrNm><codeSaleNm>분양</codeSaleNm><doroJuso>전라남도 영광군 중앙로 97</doroJuso><hoCnt>157</hoCnt><kaptAcompany>청미래주택</kaptAcompany><kaptAddr>전라남도 영광군 영광읍 녹사리 259-1 근형퍼스트빌</kaptAddr><kaptBcompany>청미래건설</kaptBcompany><kaptCode>A51380005</kaptCode><kaptDongCnt>1</kaptDongCnt><kaptFax>0613525885</kaptFax><kaptMarea>15049.96</kaptMarea><kaptMparea_135>0</kaptMparea_135><kaptMparea_136>0</kaptMparea_136><kaptMparea_60>99</kaptMparea_60><kaptMparea_85>58</kaptMparea_85><kaptName>근형퍼스트빌</kaptName><kaptTarea>15050</kaptTarea><kaptTel>0613510440</kaptTel><kaptUrl> </kaptUrl><kaptUsedate>20020408</kaptUsedate><kaptdaCnt>157</kaptdaCnt><privArea>10846.44</privArea></item></body></response>