<?xml version="1.0" encoding="UTF-8" standalone="yes"?><response><header><resultCode>00</resultCode><resultMsg>NORMAL SERVICE.</resultMsg></header><body><item><bjdCode>4615010900</bjdCode><codeAptNm>아파트</codeAptNm><codeHallNm>계단식</codeHallNm><codeHeatNm>개별난방</codeHeatNm><codeMgrNm>자치관리</codeMgrNm><codeSaleNm>분양</codeSaleNm><doroJuso>전라남도 순천시 가곡길 95</doroJuso><hoCnt>250</hoCnt><kaptAcompany>순천시</kaptAcompany><kaptAddr>전라남도 순천시 가곡동 972 가곡시영아파트</kaptAddr><kaptBcompany>순천시</kaptBcompany><kaptCode>A54008001</kaptCode><kaptDongCnt>2</kaptDongCnt><kaptFax>0619014935</kaptFax><kaptMarea>19558.8</kaptMarea><kaptMparea_135>0</kaptMparea_135><kaptMparea_136>0</kaptMparea_136><kaptMparea_60>250</kaptMparea_60><kaptMparea_85>0</kaptMparea_85><kaptName>가곡시영아파트</kaptName><kaptTarea>19559</kaptTarea><kaptTel>0619014935</kaptTel><kaptUrl> </kaptUrl><kaptUsedate>19910531</kaptUsedate><kaptdaCnt>250</kaptdaCnt><privArea>14976.3</privArea></item></body></response>