<?xml version="1.0" encoding="UTF-8" standalone="yes"?><response><header><resultCode>00</resultCode><resultMsg>NORMAL SERVICE.</resultMsg></header><body><item><bjdCode>4615031022</bjdCode><codeAptNm>아파트</codeAptNm><codeHallNm>계단식</codeHallNm><codeHeatNm>개별난방</codeHeatNm><codeMgrNm>위탁관리</codeMgrNm><codeSaleNm>분양</codeSaleNm><doroJuso>전라남도 순천시 좌야로 101</doroJuso><hoCnt>1466</hoCnt><kaptAcompany>중흥건설산업(주)</kaptAcompany><kaptAddr>전라남도 순천시 해룡면 신대리 2103 중흥S클래스1단지</kaptAddr><kaptBcompany>중흥건설산업(주)</kaptBcompany><kaptCode>A54079510</kaptCode><kaptDongCnt>13</kaptDongCnt><kaptFax>0617246446</kaptFax><kaptMarea>139515.699</kaptMarea><kaptMparea_135>0</kaptMparea_135><kaptMparea_136>0</kaptMparea_136><kaptMparea_60>561</kaptMparea_60><kaptMparea_85>905</kaptMparea_85><kaptName>중흥S클래스1단지</kaptName><kaptTarea>206021.6797</kaptTarea><kaptTel>0617245200</kaptTel><kaptUrl> </kaptUrl><kaptUsedate>20121022</kaptUsedate><kaptdaCnt>1466</kaptdaCnt><privArea>105419.7378</privArea></item></body></response>