<?xml version="1.0" encoding="UTF-8" standalone="yes"?><response><header><resultCode>00</resultCode><resultMsg>NORMAL SERVICE.</resultMsg></header><body><item><bjdCode>4613012200</bjdCode><codeAptNm>아파트</codeAptNm><codeHallNm>복도식</codeHallNm><codeHeatNm>중앙난방</codeHeatNm><codeMgrNm>위탁관리</codeMgrNm><codeSaleNm>영구임대</codeSaleNm><doroJuso>전라남도 여수시 미평로 77</doroJuso><hoCnt>537</hoCnt><kaptAcompany>한국토지주택공사</kaptAcompany><kaptAddr>전라남도 여수시 미평동 284 여수미평1관리소</kaptAddr><kaptBcompany>한국토지주택공사</kaptBcompany><kaptCode>A55024005</kaptCode><kaptDongCnt>3</kaptDongCnt><kaptFax>0616539580</kaptFax><kaptMarea>22682.32</kaptMarea><kaptMparea_135>0</kaptMparea_135><kaptMparea_136>0</kaptMparea_136><kaptMparea_60>537</kaptMparea_60><kaptMparea_85>0</kaptMparea_85><kaptName>여수미평1관리소</kaptName><kaptTarea>25556.49</kaptTarea><kaptTel>0616524568</kaptTel><kaptUrl>www.kohom.co.kr</kaptUrl><kaptUsedate>19920425</kaptUsedate><kaptdaCnt>537</kaptdaCnt><privArea>15343.74</privArea></item></body></response>