<?xml version="1.0" encoding="UTF-8" standalone="yes"?><response><header><resultCode>00</resultCode><resultMsg>NORMAL SERVICE.</resultMsg></header><body><item><bjdCode>4514031022</bjdCode><codeAptNm>아파트</codeAptNm><codeHallNm>복도식</codeHallNm><codeHeatNm>지역난방</codeHeatNm><codeMgrNm>위탁관리</codeMgrNm><codeSaleNm>임대</codeSaleNm><doroJuso>전라북도 익산시 선화로4길 14</doroJuso><hoCnt>593</hoCnt><kaptAcompany>한국토지주택공사</kaptAcompany><kaptAddr>전라북도 익산시 오산면 장신리 1126 장신휴먼시아3단지</kaptAddr><kaptBcompany>한국토지주택공사</kaptBcompany><kaptCode>A57092102</kaptCode><kaptDongCnt>7</kaptDongCnt><kaptFax>0638531226</kaptFax><kaptMarea>44421.6237</kaptMarea><kaptMparea_135>0</kaptMparea_135><kaptMparea_136>0</kaptMparea_136><kaptMparea_60>593</kaptMparea_60><kaptMparea_85>0</kaptMparea_85><kaptName>장신휴먼시아3단지</kaptName><kaptTarea>44638.93</kaptTarea><kaptTel>0638530226</kaptTel><kaptUrl>장신휴먼시아3단지.apti.co.kr</kaptUrl><kaptUsedate>20101014</kaptUsedate><kaptdaCnt>593</kaptdaCnt><privArea>25778.67</privArea></item></body></response>