<?xml version="1.0" encoding="UTF-8" standalone="yes"?><response><header><resultCode>00</resultCode><resultMsg>NORMAL SERVICE.</resultMsg></header><body><item><bjdCode>4513014400</bjdCode><codeAptNm>아파트</codeAptNm><codeHallNm>계단식</codeHallNm><codeHeatNm>개별난방</codeHeatNm><codeMgrNm>자치관리</codeMgrNm><codeSaleNm>분양</codeSaleNm><doroJuso>전라북도 군산시 나운안1길 24</doroJuso><hoCnt>636</hoCnt><kaptAcompany>(주)현대산업개발</kaptAcompany><kaptAddr>전라북도 군산시 나운동 109-6 나운4차현대아파트</kaptAddr><kaptBcompany>(주)현대산업개발</kaptBcompany><kaptCode>A57335025</kaptCode><kaptDongCnt>5</kaptDongCnt><kaptFax>0634634362</kaptFax><kaptMarea>68586.28</kaptMarea><kaptMparea_135>118</kaptMparea_135><kaptMparea_136>0</kaptMparea_136><kaptMparea_60>64</kaptMparea_60><kaptMparea_85>454</kaptMparea_85><kaptName>나운4차현대아파트</kaptName><kaptTarea>70391.88</kaptTarea><kaptTel>0634634367</kaptTel><kaptUrl> </kaptUrl><kaptUsedate>19980728</kaptUsedate><kaptdaCnt>636</kaptdaCnt><privArea>54269.49</privArea></item></body></response>