<?xml version="1.0" encoding="UTF-8" standalone="yes"?><response><header><resultCode>00</resultCode><resultMsg>NORMAL SERVICE.</resultMsg></header><body><item><bjdCode>2626010800</bjdCode><codeAptNm>아파트</codeAptNm><codeHallNm>계단식</codeHallNm><codeHeatNm>개별난방</codeHeatNm><codeMgrNm>위탁관리</codeMgrNm><codeSaleNm>분양</codeSaleNm><doroJuso>부산광역시 동래구 쇠미로129번길 91</doroJuso><hoCnt>497</hoCnt><kaptAcompany>(주)화경건설</kaptAcompany><kaptAddr>부산광역시 동래구 온천동 1654 온천삼정그린코아아파트</kaptAddr><kaptBcompany>(주)삼정</kaptBcompany><kaptCode>A60778006</kaptCode><kaptDongCnt>3</kaptDongCnt><kaptFax>0515051841</kaptFax><kaptMarea>51660.61</kaptMarea><kaptMparea_135>114</kaptMparea_135><kaptMparea_136>0</kaptMparea_136><kaptMparea_60>201</kaptMparea_60><kaptMparea_85>182</kaptMparea_85><kaptName>온천삼정그린코아아파트</kaptName><kaptTarea>60574.46</kaptTarea><kaptTel>0515051823</kaptTel><kaptUrl> </kaptUrl><kaptUsedate>20031113</kaptUsedate><kaptdaCnt>497</kaptdaCnt><privArea>39971.65</privArea></item></body></response>