<?xml version="1.0" encoding="UTF-8" standalone="yes"?><response><header><resultCode>00</resultCode><resultMsg>NORMAL SERVICE.</resultMsg></header><body><item><bjdCode>2635010700</bjdCode><codeAptNm>아파트</codeAptNm><codeHallNm>계단식</codeHallNm><codeHeatNm>지역난방</codeHeatNm><codeMgrNm>위탁관리</codeMgrNm><codeSaleNm>분양</codeSaleNm><doroJuso>부산광역시 해운대구 대천로 56</doroJuso><hoCnt>662</hoCnt><kaptAcompany>(주)한일건설</kaptAcompany><kaptAddr>부산광역시 해운대구 좌동 1274 해운대한일아파트</kaptAddr><kaptBcompany>(주)한일건설</kaptBcompany><kaptCode>A61203015</kaptCode><kaptDongCnt>11</kaptDongCnt><kaptFax>0517478312</kaptFax><kaptMarea>75217.2</kaptMarea><kaptMparea_135>183</kaptMparea_135><kaptMparea_136>41</kaptMparea_136><kaptMparea_60>300</kaptMparea_60><kaptMparea_85>138</kaptMparea_85><kaptName>해운대한일아파트</kaptName><kaptTarea>96338.349</kaptTarea><kaptTel>0517478311</kaptTel><kaptUrl> </kaptUrl><kaptUsedate>19960629</kaptUsedate><kaptdaCnt>662</kaptdaCnt><privArea>59436.78</privArea></item></body></response>