<?xml version="1.0" encoding="UTF-8" standalone="yes"?><response><header><resultCode>00</resultCode><resultMsg>NORMAL SERVICE.</resultMsg></header><body><item><bjdCode>2653010200</bjdCode><codeAptNm>아파트</codeAptNm><codeHallNm>계단식</codeHallNm><codeHeatNm>개별난방</codeHeatNm><codeMgrNm>위탁관리</codeMgrNm><codeSaleNm>분양</codeSaleNm><doroJuso>부산광역시 사상구 백양대로934번길 84</doroJuso><hoCnt>780</hoCnt><kaptAcompany>대한주택보증</kaptAcompany><kaptAddr>부산광역시 사상구 모라동 203 모라벽산아파트</kaptAddr><kaptBcompany>벽산건설</kaptBcompany><kaptCode>A61781805</kaptCode><kaptDongCnt>8</kaptDongCnt><kaptFax>0513120360</kaptFax><kaptMarea>79287.69</kaptMarea><kaptMparea_135>84</kaptMparea_135><kaptMparea_136>0</kaptMparea_136><kaptMparea_60>270</kaptMparea_60><kaptMparea_85>426</kaptMparea_85><kaptName>모라벽산아파트</kaptName><kaptTarea>103998.7</kaptTarea><kaptTel>0513120359</kaptTel><kaptUrl> </kaptUrl><kaptUsedate>20010915</kaptUsedate><kaptdaCnt>780</kaptdaCnt><privArea>62568.72</privArea></item></body></response>