<?xml version="1.0" encoding="UTF-8" standalone="yes"?><response><header><resultCode>00</resultCode><resultMsg>NORMAL SERVICE.</resultMsg></header><body><item><bjdCode>4812725026</bjdCode><codeAptNm>아파트</codeAptNm><codeHallNm>계단식</codeHallNm><codeHeatNm>개별난방</codeHeatNm><codeMgrNm>자치관리</codeMgrNm><codeSaleNm>분양</codeSaleNm><doroJuso>경상남도 창원시 마산회원구 상곡로 5</doroJuso><hoCnt>150</hoCnt><kaptAcompany>동남종합건설주식회사</kaptAcompany><kaptAddr>경상남도 창원마산회원구 내서읍 상곡리 196 동남타운</kaptAddr><kaptBcompany>동남종합건설주식회사</kaptBcompany><kaptCode>A63085401</kaptCode><kaptDongCnt>1</kaptDongCnt><kaptFax>0552320527</kaptFax><kaptMarea>10909.2</kaptMarea><kaptMparea_135>0</kaptMparea_135><kaptMparea_136>0</kaptMparea_136><kaptMparea_60>150</kaptMparea_60><kaptMparea_85>0</kaptMparea_85><kaptName>동남타운</kaptName><kaptTarea>10953.97</kaptTarea><kaptTel>0552320527</kaptTel><kaptUrl> </kaptUrl><kaptUsedate>19960417</kaptUsedate><kaptdaCnt>150</kaptdaCnt><privArea>8997.15</privArea></item></body></response>