<?xml version="1.0" encoding="UTF-8" standalone="yes"?><response><header><resultCode>00</resultCode><resultMsg>NORMAL SERVICE.</resultMsg></header><body><item><bjdCode>4812915800</bjdCode><codeAptNm>아파트</codeAptNm><codeHallNm>계단식</codeHallNm><codeHeatNm>개별난방</codeHeatNm><codeMgrNm>위탁관리</codeMgrNm><codeSaleNm>분양</codeSaleNm><doroJuso>경상남도 창원시 진해구 마천로 50</doroJuso><hoCnt>468</hoCnt><kaptAcompany>경남기업(주)</kaptAcompany><kaptAddr>경상남도 창원진해구 마천동 246 경남아너스빌</kaptAddr><kaptBcompany>경남기업(주)</kaptBcompany><kaptCode>A64545001</kaptCode><kaptDongCnt>9</kaptDongCnt><kaptFax>0555425072</kaptFax><kaptMarea>48123.2</kaptMarea><kaptMparea_135>0</kaptMparea_135><kaptMparea_136>0</kaptMparea_136><kaptMparea_60>180</kaptMparea_60><kaptMparea_85>288</kaptMparea_85><kaptName>경남아너스빌</kaptName><kaptTarea>59675</kaptTarea><kaptTel>0555425071</kaptTel><kaptUrl> </kaptUrl><kaptUsedate>20080829</kaptUsedate><kaptdaCnt>468</kaptdaCnt><privArea>35169.8688</privArea></item></body></response>