<?xml version="1.0" encoding="UTF-8" standalone="yes"?><response><header><resultCode>00</resultCode><resultMsg>NORMAL SERVICE.</resultMsg></header><body><item><bjdCode>3117010100</bjdCode><codeAptNm>아파트</codeAptNm><codeHallNm>복도식</codeHallNm><codeHeatNm>개별난방</codeHeatNm><codeMgrNm>위탁관리</codeMgrNm><codeSaleNm>분양</codeSaleNm><doroJuso>울산광역시 동구 화잠9길 45</doroJuso><hoCnt>351</hoCnt><kaptAcompany>현대미포조선</kaptAcompany><kaptAddr>울산광역시 동구 방어동 971 꽃바위현대</kaptAddr><kaptBcompany>현대산업개발</kaptBcompany><kaptCode>A68280603</kaptCode><kaptDongCnt>4</kaptDongCnt><kaptFax>0529981211</kaptFax><kaptMarea>29008.395</kaptMarea><kaptMparea_135>0</kaptMparea_135><kaptMparea_136>0</kaptMparea_136><kaptMparea_60>351</kaptMparea_60><kaptMparea_85>0</kaptMparea_85><kaptName>꽃바위현대</kaptName><kaptTarea>29715.016</kaptTarea><kaptTel>0529911211</kaptTel><kaptUrl> </kaptUrl><kaptUsedate>19950906</kaptUsedate><kaptdaCnt>351</kaptdaCnt><privArea>20954.7</privArea></item></body></response>