<?xml version="1.0" encoding="UTF-8" standalone="yes"?><response><header><resultCode>00</resultCode><resultMsg>NORMAL SERVICE.</resultMsg></header><body><item><bjdCode>2729010700</bjdCode><codeAptNm>아파트</codeAptNm><codeHallNm>복도식</codeHallNm><codeHeatNm>지역난방</codeHeatNm><codeMgrNm>위탁관리</codeMgrNm><codeSaleNm>임대</codeSaleNm><doroJuso>대구광역시 달서구 신당로 56</doroJuso><hoCnt>1877</hoCnt><kaptAcompany>한국토지주택공사</kaptAcompany><kaptAddr>대구광역시 달서구 신당동 1844 대구성서1</kaptAddr><kaptBcompany>서한</kaptBcompany><kaptCode>A70474903</kaptCode><kaptDongCnt>13</kaptDongCnt><kaptFax>0532837753</kaptFax><kaptMarea>84359.782</kaptMarea><kaptMparea_135>0</kaptMparea_135><kaptMparea_136>0</kaptMparea_136><kaptMparea_60>1877</kaptMparea_60><kaptMparea_85>0</kaptMparea_85><kaptName>대구성서1</kaptName><kaptTarea>87795.59</kaptTarea><kaptTel>0535817150</kaptTel><kaptUrl>www.kohom.co.kr</kaptUrl><kaptUsedate>19950504</kaptUsedate><kaptdaCnt>1877</kaptdaCnt><privArea>57027.79</privArea></item></body></response>