<?xml version="1.0" encoding="UTF-8" standalone="yes"?><response><header><resultCode>00</resultCode><resultMsg>NORMAL SERVICE.</resultMsg></header><body><item><bjdCode>2720010200</bjdCode><codeAptNm>아파트</codeAptNm><codeHallNm>계단식</codeHallNm><codeHeatNm>중앙난방</codeHeatNm><codeMgrNm>자치관리</codeMgrNm><codeSaleNm>분양</codeSaleNm><doroJuso>대구광역시 남구 앞산순환로 657</doroJuso><hoCnt>528</hoCnt><kaptAcompany>보성주택</kaptAcompany><kaptAddr>대구광역시 남구 봉덕동 1329-2 1차대덕맨션</kaptAddr><kaptBcompany>보성주택</kaptBcompany><kaptCode>A70575204</kaptCode><kaptDongCnt>6</kaptDongCnt><kaptFax>0534711176</kaptFax><kaptMarea>69719.322</kaptMarea><kaptMparea_135>172</kaptMparea_135><kaptMparea_136>30</kaptMparea_136><kaptMparea_60>0</kaptMparea_60><kaptMparea_85>326</kaptMparea_85><kaptName>1차대덕맨션</kaptName><kaptTarea>70656.021</kaptTarea><kaptTel>0534711174</kaptTel><kaptUrl> </kaptUrl><kaptUsedate>19900920</kaptUsedate><kaptdaCnt>528</kaptdaCnt><privArea>54674.66</privArea></item></body></response>