<?xml version="1.0" encoding="UTF-8" standalone="yes"?><response><header><resultCode>00</resultCode><resultMsg>NORMAL SERVICE.</resultMsg></header><body><item><bjdCode>4773025022</bjdCode><codeAptNm>아파트</codeAptNm><codeHallNm>복도식</codeHallNm><codeHeatNm>개별난방</codeHeatNm><codeMgrNm>위탁관리</codeMgrNm><codeSaleNm>분양</codeSaleNm><doroJuso>경상북도 의성군 충효로 75</doroJuso><hoCnt>281</hoCnt><kaptAcompany>(주)대일주택</kaptAcompany><kaptAddr>경상북도 의성군 의성읍 중리리 735-1 의성청구제네스</kaptAddr><kaptBcompany>(주)청구</kaptBcompany><kaptCode>A76980303</kaptCode><kaptDongCnt>2</kaptDongCnt><kaptFax>0548335648</kaptFax><kaptMarea>22892.56</kaptMarea><kaptMparea_135>0</kaptMparea_135><kaptMparea_136>0</kaptMparea_136><kaptMparea_60>251</kaptMparea_60><kaptMparea_85>30</kaptMparea_85><kaptName>의성청구제네스</kaptName><kaptTarea>25086.7</kaptTarea><kaptTel>0548335648</kaptTel><kaptUrl> </kaptUrl><kaptUsedate>20031216</kaptUsedate><kaptdaCnt>281</kaptdaCnt><privArea>17038.78</privArea></item></body></response>